adafruit_fingerprint/__init__.py
adafruit_fingerprint/core.py
adafruit_fingerprint/exceptions.py
adafruit_fingerprint/interface.py
adafruit_fingerprint/responses.py
adafruit_fingerprint/utils.py
adafruit_fingerprint-1.0.3.dist-info/LICENSE
adafruit_fingerprint-1.0.3.dist-info/METADATA
adafruit_fingerprint-1.0.3.dist-info/WHEEL
adafruit_fingerprint-1.0.3.dist-info/top_level.txt
adafruit_fingerprint-1.0.3.dist-info/RECORD
