Metadata-Version: 2.1
Name: adafruit-fingerprint
Version: 1.0.3
Summary: Interface with the adafruit fingerprint r305 module from upper computer over serial connection
Home-page: https://github.com/cerebrohivetech/adafruit-fingerprint
Author: Faith Odonghanro, Promise Nwanozie, Joshua Adegoke
Author-email: toriboi.fo@gmail.com
License: MIT
Project-URL: Documentation, https://adafruit-fingerprint.readthedocs.io
Project-URL: Repository, https://github.com/cerebrohivetech/adafruit-fingerprint
Classifier: License :: OSI Approved :: MIT License
Classifier: Programming Language :: Python :: 3
Classifier: Programming Language :: Python :: 3.6
License-File: LICENSE
Requires-Dist: pyserial==3.4.0
